README.md
setup.py
aiodtnsim/__init__.py
aiodtnsim/timeutil.py
aiodtnsim.egg-info/PKG-INFO
aiodtnsim.egg-info/SOURCES.txt
aiodtnsim.egg-info/dependency_links.txt
aiodtnsim.egg-info/requires.txt
aiodtnsim.egg-info/top_level.txt
aiodtnsim/emulation/__init__.py
aiodtnsim/emulation/aio_upcn_interface.py
aiodtnsim/emulation/upcn_node.py
aiodtnsim/reports/__init__.py
aiodtnsim/reports/logging.py
aiodtnsim/reports/message_ops_report.py
aiodtnsim/reports/message_stats_report.py
aiodtnsim/simulation/__init__.py
aiodtnsim/simulation/epidemic_node.py
aiodtnsim/simulation/event_loop.py
aiodtnsim/simulation/one_epidemic_node.py
aiodtnsim/simulation/one_sprayandwait_node.py
aiodtnsim/simulation/opportunistic_node.py
aiodtnsim/simulation/scheduling_event_node.py
aiodtnsim/simulation/simplified_epidemic_node.py
aiodtnsim/simulation/sprayandwait_node.py
aiodtnsim/simulation/util.py
aiodtnsim/simulation/cgr/__init__.py
aiodtnsim/simulation/cgr/sabr.py
aiodtnsim/simulation/cgr/sabr_nodegraph_node.py
aiodtnsim/simulation/cgr/sabr_nodegraph_node_yen.py
aiodtnsim/simulation/cgr/sabr_probcgr_node.py
aiodtnsim/simulation/cgr/tvdijkstra.py
aiodtnsim/simulation/link/__init__.py
aiodtnsim/simulation/link/impaired_cla_link.py
test/__init__.py
test/test_basenode.py
test/test_contact.py
test/test_eventdispatcher.py
test/test_timeutil.py
test/util.py
test/simulation/__init__.py