Metadata-Version: 2.1
Name: aiodtnsim
Version: 0.3.1
Summary: A framework for performing DTN simulations based on asyncio.
Home-page: https://gitlab.com/d3tn/aiodtnsim
Author: Felix Walter
Author-email: code@felix-walter.eu
License: UNKNOWN
Platform: UNKNOWN
Classifier: Programming Language :: Python :: 3
Classifier: License :: OSI Approved :: MIT License
Classifier: Operating System :: OS Independent
Requires-Python: >=3.7
